Metadata-Version: 2.1
Name: empirical-init
Version: 0.0.2
Summary: Automatically initialize weights in pytorch modules using a hacky empirical method.
Home-page: https://github.com/pb1729/empirical-init
Author: Phillip Bement
Author-email: {author_first_name}{author_last_initial}@fastmail.com
License: BSD 3-clause
License-File: LICENSE
